{
	"info": {
		"_postman_id": "ce492b8f-744f-4710-8bca-4647bacdb81c",
		"name": "TestCollection",
		"schema": "https://schema.getpostman.com/json/collection/v2.1.0/collection.json",
		"_exporter_id": "20344132"
	},
	"item": [
		{
			"name": "TestCollection",
			"event": [
				{
					"listen": "test",
					"script": {
						"exec": [
							"pm.test(\"Response check\", function(){",
							"",
							"    pm.response.to.have.status(200);",
							"    pm.response.to.have.body('22')",
							"})"
						],
						"type": "text/javascript"
					}
				}
			],
			"request": {
				"method": "GET",
				"header": [
					{
						"key": "X-Auth-token",
						"value": "825290c1b253821ebcb6a07a423eb7a690a41795",
						"type": "text",
						"disabled": true
					},
					{
						"key": "Authorization",
						"value": "Bearer a12987e9fe6a4d28b0f2f736d2f823b638f886c9",
						"type": "text"
					}
				],
				"url": {
					"raw": "http://localhost:1027/v2/entities/",
					"protocol": "http",
					"host": [
						"localhost"
					],
					"port": "1027",
					"path": [
						"v2",
						"entities",
						""
					]
				}
			},
			"response": []
		},
		{
			"name": "Get Token",
			"request": {
				"method": "POST",
				"header": [
					{
						"key": "Authorization",
						"value": "Basic 9b6e4b9ab6017273d525c6457a50f1d50c54a7a1",
						"type": "text",
						"disabled": true
					},
					{
						"key": "",
						"value": "",
						"type": "text",
						"disabled": true
					},
					{
						"key": "",
						"value": "",
						"type": "text",
						"disabled": true
					}
				],
				"body": {
					"mode": "urlencoded",
					"urlencoded": [
						{
							"key": "username",
							"value": "alice-the-admin@test.com",
							"type": "text"
						},
						{
							"key": "password",
							"value": "test",
							"type": "text"
						},
						{
							"key": "grant_type",
							"value": "password",
							"type": "text"
						},
						{
							"key": "scope",
							"value": "permanent",
							"type": "text"
						},
						{
							"key": "client_id",
							"value": "tutorial-dckr-site-0000-xpresswebapp",
							"type": "text"
						},
						{
							"key": "client_secret",
							"value": "tutorial-dckr-site-0000-clientsecret",
							"type": "text"
						}
					]
				},
				"url": {
					"raw": "http://localhost:3005/oauth2/token",
					"protocol": "http",
					"host": [
						"localhost"
					],
					"port": "3005",
					"path": [
						"oauth2",
						"token"
					]
				}
			},
			"response": []
		},
		{
			"name": "Get Token Updaters",
			"request": {
				"method": "POST",
				"header": [
					{
						"key": "Authorization",
						"value": "Basic 9b6e4b9ab6017273d525c6457a50f1d50c54a7a1",
						"type": "text",
						"disabled": true
					},
					{
						"key": "",
						"value": "",
						"type": "text",
						"disabled": true
					},
					{
						"key": "",
						"value": "",
						"type": "text",
						"disabled": true
					}
				],
				"body": {
					"mode": "urlencoded",
					"urlencoded": [
						{
							"key": "username",
							"value": "date-the-updater@test.com",
							"type": "text"
						},
						{
							"key": "password",
							"value": "test",
							"type": "text"
						},
						{
							"key": "grant_type",
							"value": "password",
							"type": "text"
						},
						{
							"key": "scope",
							"value": "permanent",
							"type": "text",
							"disabled": true
						},
						{
							"key": "client_id",
							"value": "e771844b-90b2-4d94-a656-9c2cfd9f2fda",
							"type": "text"
						},
						{
							"key": "client_secret",
							"value": "e37ea5f4-76ee-4010-8cfa-421ce6e5dda8",
							"type": "text"
						}
					]
				},
				"url": {
					"raw": "http://localhost:3005/oauth2/token",
					"protocol": "http",
					"host": [
						"localhost"
					],
					"port": "3005",
					"path": [
						"oauth2",
						"token"
					]
				}
			},
			"response": []
		},
		{
			"name": "Get Auth",
			"request": {
				"method": "GET",
				"header": [],
				"url": {
					"raw": "http://localhost:3005/oauth2/authorize?response_type=token&client_id=tutorial-dckr-site-0000-xpresswebapp&state=1&redirect_uri=http://localhost:3005&scope=permanent",
					"protocol": "http",
					"host": [
						"localhost"
					],
					"port": "3005",
					"path": [
						"oauth2",
						"authorize"
					],
					"query": [
						{
							"key": "response_type",
							"value": "token"
						},
						{
							"key": "client_id",
							"value": "tutorial-dckr-site-0000-xpresswebapp"
						},
						{
							"key": "state",
							"value": "1"
						},
						{
							"key": "redirect_uri",
							"value": "http://localhost:3005"
						},
						{
							"key": "scope",
							"value": "permanent"
						}
					]
				}
			},
			"response": []
		}
	]
}